[
  { "goalName": "Emergency Fund", "targetAmount": 50000, "currentAmount": 35000, "deadline": "2025-12-31", "priority": "High" },
  { "goalName": "House Down Payment", "targetAmount": 200000, "currentAmount": 120000, "deadline": "2026-06-30", "priority": "High" },
  { "goalName": "Retirement Fund", "targetAmount": 1000000, "currentAmount": 450000, "deadline": "2040-12-31", "priority": "Medium" },
  { "goalName": "Children's Education", "targetAmount": 300000, "currentAmount": 85000, "deadline": "2030-12-31", "priority": "High" },
  { "goalName": "Vacation Fund", "targetAmount": 15000, "currentAmount": 8000, "deadline": "2025-08-31", "priority": "Low" },
  { "goalName": "Car Purchase", "targetAmount": 80000, "currentAmount": 25000, "deadline": "2025-10-31", "priority": "Medium" },
  { "goalName": "Investment Portfolio", "targetAmount": 500000, "currentAmount": 280000, "deadline": "2027-12-31", "priority": "Medium" },
  { "goalName": "Wedding Fund", "targetAmount": 40000, "currentAmount": 15000, "deadline": "2026-03-31", "priority": "High" },
  { "goalName": "Business Startup", "targetAmount": 100000, "currentAmount": 35000, "deadline": "2026-09-30", "priority": "Medium" },
  { "goalName": "Home Renovation", "targetAmount": 60000, "currentAmount": 20000, "deadline": "2025-11-30", "priority": "Low" }
]
